dnslookup/DNSLookupBase.py
dnslookup/Domain.py
dnslookup/NameServer.py
dnslookup/NameServerCollection.py
dnslookup/__init__.py
dnslookup/__main__.py
dnslookup/lookup_util.py
dnslookup-0.7.42.dist-info/LICENSE.txt
dnslookup-0.7.42.dist-info/METADATA
dnslookup-0.7.42.dist-info/WHEEL
dnslookup-0.7.42.dist-info/entry_points.txt
dnslookup-0.7.42.dist-info/top_level.txt
dnslookup-0.7.42.dist-info/RECORD
