Metadata-Version: 2.1
Name: dnslookup
Version: 0.7.42
Summary: Check dns entries across the world. In short, if you move your server from one IP to another, you can check to see when most of the dns servers in the world have update their results.
Home-page: https://github.com/joubin/DNSPython
Author: Joubin Jabbari
Author-email: joubin.j@gmail.com
License: LICENSE.txt
Platform: UNKNOWN
Classifier: Programming Language :: Python :: 3.7
Classifier: Programming Language :: Python :: 2.7
Classifier: License :: OSI Approved :: MIT License
Classifier: Operating System :: OS Independent
Requires-Dist: dnspython
